{"name":"EVO75","vendorProductId":917516574,"firmwareVersion":0,"menus":[{"label":"Lighting","content":[{"label":"RGB Strip","content":[{"showIf":"{id_qmk_rgblight_effect} != 0","label":"Brightness","type":"range","options":[0,105],"content":["id_qmk_rgblight_brightness",2,1]},{"label":"Effect","type":"dropdown","content":["id_qmk_rgblight_effect",2,2],"options":[["none",0],["wave_rgb",1],["wave_1",2],["wave_2",3],["fixed ds",4],["fixed wave",5],["spectrum",6],["breathe",7],["breathe_mix",8],["light",9],["shutdown",10]]},{"showIf":"{id_qmk_rgblight_effect} != 0","label":"Effect Speed","type":"range","options":[0,4],"content":["id_qmk_rgblight_effect_speed",2,3]},{"showIf":"{id_qmk_rgblight_effect} != 0 && {id_qmk_rgblight_effect} != 1 && {id_qmk_rgblight_effect} != 3 && {id_qmk_rgblight_effect} != 6","label":"Color","type":"color","content":["id_qmk_rgblight_color",2,4]}]},{"label":"Per-Key RGB","content":[{"label":"Brightness","type":"range","options":[0,128],"content":["id_qmk_rgb_matrix_brightness",3,1]},{"label":"Effect","type":"dropdown","content":["id_qmk_rgb_matrix_effect",3,2],"options":[["ALL RGB OFF",0],["solid_color",1],["alphas_mods",2],["gradient_up_down",3],["gradient_left_right",4],["breathing",5],["band_sat",6],["band_val",7],["band_pinwheel_sat",8],["band_pinwheel_val",9],["band_spiral_sat",10],["band_spiral_val",11],["cycle_all",12],["cycle_left_right",13],["cycle_up_down",14],["cycle_out_in",15],["cycle_out_in_dual",16],["rainbow_moving_chevron",17],["cycle_pinwheel",18],["cycle_spiral",19],["dual_beacon",20],["rainbow_beacon",21],["rainbow_pinwheels",22],["flower_blooming",23],["raindrops",24],["jellybean_raindrops",25],["hue_breathing",26],["hue_pendulum",27],["hue_wave",28],["pixel_flow",29],["digital_rain",30],["solid_reactive",31],["solid_reactive_wide",32],["solid_reactive_multiwide",33],["solid_reactive_cross",34],["solid_reactive_multicross",35],["solid_reactive_nexus",36],["solid_reactive_multinexus",37],["splash",38],["multisplash",39],["solid_splash",40],["solid_multisplash",41],["riverflow",42]]},{"showIf":"{id_qmk_rgb_matrix_effect} != 0","label":"Effect Speed","type":"range","options":[0,255],"content":["id_qmk_rgb_matrix_effect_speed",3,3]},{"showIf":"{id_qmk_rgb_matrix_effect} != 0 && {id_qmk_rgb_matrix_effect} != 24 && {id_qmk_rgb_matrix_effect} != 28 && {id_qmk_rgb_matrix_effect} != 29 && {id_qmk_rgb_matrix_effect} != 32","label":"Color","type":"color","content":["id_qmk_rgb_matrix_color",3,4]}]}]}],"keycodes":["qmk_lighting"],"customKeycodes":[{"name":"2.4G","title":"Set to 2.4G working mode","shortName":"MD_24G"},{"name":"BLE1","title":"Set to Bluetooth Channel 1 working mode","shortName":"MD_BLE1"},{"name":"BLE2","title":"Set to Bluetooth Channel 2 working mode","shortName":"MD_BLE2"},{"name":"BLE3","title":"Set to Bluetooth Channel 3 working mode","shortName":"MD_BLE3"},{"name":"USB","title":"Set to USB working mode","shortName":"MD_USB"},{"name":"BAT","title":"Querying Battery Status","shortName":"QK_BAT"},{"name":"WLO","title":"Lock WIN","shortName":"QK_WLO"},{"name":"SIX_N","title":"Full-key six-key switch","shortName":"SIX_N"},{"name":"TEST","title":"Test Keyboard Colour","shortName":"TEST"},{"name":"KbPrSlp","title":"Keyboard primary sleep","shortName":"KbPrSlp"},{"name":"KbdSecS","title":"Keyboard secondary sleep","shortName":"KbdSecS"},{"name":"IOS_SIRI","title":"Outgoing SIRI","shortName":"SIRI"},{"name":"RTOG","title":"Toggle led lighting on or off","shortName":"RGB_RTOG"},{"name":"QK_DEB","title":"Number of times that the key shakes off","shortName":"QK_DEB"},{"name":"LG_TOG","title":"Toggle logo lighting on or off","shortName":"LG_TOG"},{"name":"LG_MO","title":"Cycle through modes","shortName":"LG_MOD"},{"name":"LG_RM","title":"Cycle through modes in reverse","shortName":"LG_RMOD"},{"name":"LG_HUI","title":"logo Increase hue","shortName":"LG_HUI"},{"name":"LG_HUD","title":"logo Decrease hue","shortName":"LG_HUD"},{"name":"LG_SAI","title":"logo Increase saturation","shortName":"LG_SAI"},{"name":"LG_SAD","title":"logo Decrease saturation","shortName":"LG_SAD"},{"name":"LG_VAI","title":"logo Increase value (brightness)","shortName":"LG_VAI"},{"name":"LG_VAD","title":"logo Decrease value (brightness)","shortName":"LG_VAD"},{"name":"LG_SPI","title":"logo Increase effect speed","shortName":"LG_SPI"},{"name":"LG_SPD","title":"logo Decrease effect speed","shortName":"LG_SPD"}],"matrix":{"rows":6,"cols":16},"layouts":{"width":16,"height":6.25,"optionKeys":{},"keys":[{"row":0,"col":0,"x":0,"y":0,"r":0,"rx":0,"ry":0,"d":false,"h":1,"w":1,"color":"accent"},{"row":0,"col":1,"x":1.75,"y":0,"r":0,"rx":0,"ry":0,"d":false,"h":1,"w":1,"color":"mod"},{"row":0,"col":2,"x":2.75,"y":0,"r":0,"rx":0,"ry":0,"d":false,"h":1,"w":1,"color":"mod"},{"row":0,"col":3,"x":3.75,"y":0,"r":0,"rx":0,"ry":0,"d":false,"h":1,"w":1,"color":"mod"},{"row":0,"col":4,"x":4.75,"y":0,"r":0,"rx":0,"ry":0,"d":false,"h":1,"w":1,"color":"mod"},{"row":0,"col":5,"x":6,"y":0,"r":0,"rx":0,"ry":0,"d":false,"h":1,"w":1,"color":"mod"},{"row":0,"col":6,"x":7,"y":0,"r":0,"rx":0,"ry":0,"d":false,"h":1,"w":1,"color":"mod"},{"row":0,"col":7,"x":8,"y":0,"r":0,"rx":0,"ry":0,"d":false,"h":1,"w":1,"color":"mod"},{"row":0,"col":8,"x":9,"y":0,"r":0,"rx":0,"ry":0,"d":false,"h":1,"w":1,"color":"mod"},{"row":0,"col":9,"x":10.25,"y":0,"r":0,"rx":0,"ry":0,"d":false,"h":1,"w":1,"color":"mod"},{"row":0,"col":10,"x":11.25,"y":0,"r":0,"rx":0,"ry":0,"d":false,"h":1,"w":1,"color":"mod"},{"row":0,"col":11,"x":12.25,"y":0,"r":0,"rx":0,"ry":0,"d":false,"h":1,"w":1,"color":"mod"},{"row":0,"col":12,"x":13.25,"y":0,"r":0,"rx":0,"ry":0,"d":false,"h":1,"w":1,"color":"mod"},{"row":2,"col":14,"x":15,"y":0,"r":0,"rx":0,"ry":0,"d":false,"h":1,"w":1,"color":"mod"},{"row":1,"col":0,"x":0,"y":1.25,"r":0,"rx":0,"ry":0,"d":false,"h":1,"w":1,"color":"alpha"},{"row":1,"col":1,"x":1,"y":1.25,"r":0,"rx":0,"ry":0,"d":false,"h":1,"w":1,"color":"alpha"},{"row":1,"col":2,"x":2,"y":1.25,"r":0,"rx":0,"ry":0,"d":false,"h":1,"w":1,"color":"alpha"},{"row":1,"col":3,"x":3,"y":1.25,"r":0,"rx":0,"ry":0,"d":false,"h":1,"w":1,"color":"alpha"},{"row":1,"col":4,"x":4,"y":1.25,"r":0,"rx":0,"ry":0,"d":false,"h":1,"w":1,"color":"alpha"},{"row":1,"col":5,"x":5,"y":1.25,"r":0,"rx":0,"ry":0,"d":false,"h":1,"w":1,"color":"alpha"},{"row":1,"col":6,"x":6,"y":1.25,"r":0,"rx":0,"ry":0,"d":false,"h":1,"w":1,"color":"alpha"},{"row":1,"col":7,"x":7,"y":1.25,"r":0,"rx":0,"ry":0,"d":false,"h":1,"w":1,"color":"alpha"},{"row":1,"col":8,"x":8,"y":1.25,"r":0,"rx":0,"ry":0,"d":false,"h":1,"w":1,"color":"alpha"},{"row":1,"col":9,"x":9,"y":1.25,"r":0,"rx":0,"ry":0,"d":false,"h":1,"w":1,"color":"alpha"},{"row":1,"col":10,"x":10,"y":1.25,"r":0,"rx":0,"ry":0,"d":false,"h":1,"w":1,"color":"alpha"},{"row":1,"col":11,"x":11,"y":1.25,"r":0,"rx":0,"ry":0,"d":false,"h":1,"w":1,"color":"alpha"},{"row":1,"col":12,"x":12,"y":1.25,"r":0,"rx":0,"ry":0,"d":false,"h":1,"w":1,"color":"alpha"},{"row":1,"col":13,"x":13,"y":1.25,"r":0,"rx":0,"ry":0,"d":false,"h":1,"w":2,"color":"mod"},{"row":2,"col":15,"x":15,"y":1.25,"r":0,"rx":0,"ry":0,"d":false,"h":1,"w":1,"color":"mod"},{"row":2,"col":0,"x":0,"y":2.25,"r":0,"rx":0,"ry":0,"d":false,"h":1,"w":1.5,"color":"mod"},{"row":2,"col":1,"x":1.5,"y":2.25,"r":0,"rx":0,"ry":0,"d":false,"h":1,"w":1,"color":"alpha"},{"row":2,"col":2,"x":2.5,"y":2.25,"r":0,"rx":0,"ry":0,"d":false,"h":1,"w":1,"color":"alpha"},{"row":2,"col":3,"x":3.5,"y":2.25,"r":0,"rx":0,"ry":0,"d":false,"h":1,"w":1,"color":"alpha"},{"row":2,"col":4,"x":4.5,"y":2.25,"r":0,"rx":0,"ry":0,"d":false,"h":1,"w":1,"color":"alpha"},{"row":2,"col":5,"x":5.5,"y":2.25,"r":0,"rx":0,"ry":0,"d":false,"h":1,"w":1,"color":"alpha"},{"row":2,"col":6,"x":6.5,"y":2.25,"r":0,"rx":0,"ry":0,"d":false,"h":1,"w":1,"color":"alpha"},{"row":2,"col":7,"x":7.5,"y":2.25,"r":0,"rx":0,"ry":0,"d":false,"h":1,"w":1,"color":"alpha"},{"row":2,"col":8,"x":8.5,"y":2.25,"r":0,"rx":0,"ry":0,"d":false,"h":1,"w":1,"color":"alpha"},{"row":2,"col":9,"x":9.5,"y":2.25,"r":0,"rx":0,"ry":0,"d":false,"h":1,"w":1,"color":"alpha"},{"row":2,"col":10,"x":10.5,"y":2.25,"r":0,"rx":0,"ry":0,"d":false,"h":1,"w":1,"color":"alpha"},{"row":2,"col":11,"x":11.5,"y":2.25,"r":0,"rx":0,"ry":0,"d":false,"h":1,"w":1,"color":"alpha"},{"row":2,"col":12,"x":12.5,"y":2.25,"r":0,"rx":0,"ry":0,"d":false,"h":1,"w":1,"color":"alpha"},{"row":3,"col":13,"x":13.5,"y":2.25,"r":0,"rx":0,"ry":0,"d":false,"h":2,"w":1.25,"w2":1.5,"x2":0,"h2":1,"color":"accent"},{"row":3,"col":14,"x":15,"y":2.25,"r":0,"rx":0,"ry":0,"d":false,"h":1,"w":1,"color":"mod"},{"row":3,"col":0,"x":0,"y":3.25,"r":0,"rx":0,"ry":0,"d":false,"h":1,"w":1.75,"color":"mod"},{"row":3,"col":1,"x":1.75,"y":3.25,"r":0,"rx":0,"ry":0,"d":false,"h":1,"w":1,"color":"alpha"},{"row":3,"col":2,"x":2.75,"y":3.25,"r":0,"rx":0,"ry":0,"d":false,"h":1,"w":1,"color":"alpha"},{"row":3,"col":3,"x":3.75,"y":3.25,"r":0,"rx":0,"ry":0,"d":false,"h":1,"w":1,"color":"alpha"},{"row":3,"col":4,"x":4.75,"y":3.25,"r":0,"rx":0,"ry":0,"d":false,"h":1,"w":1,"color":"alpha"},{"row":3,"col":5,"x":5.75,"y":3.25,"r":0,"rx":0,"ry":0,"d":false,"h":1,"w":1,"color":"alpha"},{"row":3,"col":6,"x":6.75,"y":3.25,"r":0,"rx":0,"ry":0,"d":false,"h":1,"w":1,"color":"alpha"},{"row":3,"col":7,"x":7.75,"y":3.25,"r":0,"rx":0,"ry":0,"d":false,"h":1,"w":1,"color":"alpha"},{"row":3,"col":8,"x":8.75,"y":3.25,"r":0,"rx":0,"ry":0,"d":false,"h":1,"w":1,"color":"alpha"},{"row":3,"col":9,"x":9.75,"y":3.25,"r":0,"rx":0,"ry":0,"d":false,"h":1,"w":1,"color":"alpha"},{"row":3,"col":10,"x":10.75,"y":3.25,"r":0,"rx":0,"ry":0,"d":false,"h":1,"w":1,"color":"alpha"},{"row":3,"col":11,"x":11.75,"y":3.25,"r":0,"rx":0,"ry":0,"d":false,"h":1,"w":1,"color":"alpha"},{"row":3,"col":12,"x":12.75,"y":3.25,"r":0,"rx":0,"ry":0,"d":false,"h":1,"w":1,"color":"alpha"},{"row":3,"col":15,"x":15,"y":3.25,"r":0,"rx":0,"ry":0,"d":false,"h":1,"w":1,"color":"mod"},{"row":4,"col":0,"x":0,"y":4.25,"r":0,"rx":0,"ry":0,"d":false,"h":1,"w":1.25,"color":"mod"},{"row":4,"col":1,"x":1.25,"y":4.25,"r":0,"rx":0,"ry":0,"d":false,"h":1,"w":1,"color":"alpha"},{"row":4,"col":2,"x":2.25,"y":4.25,"r":0,"rx":0,"ry":0,"d":false,"h":1,"w":1,"color":"alpha"},{"row":4,"col":3,"x":3.25,"y":4.25,"r":0,"rx":0,"ry":0,"d":false,"h":1,"w":1,"color":"alpha"},{"row":4,"col":4,"x":4.25,"y":4.25,"r":0,"rx":0,"ry":0,"d":false,"h":1,"w":1,"color":"alpha"},{"row":4,"col":5,"x":5.25,"y":4.25,"r":0,"rx":0,"ry":0,"d":false,"h":1,"w":1,"color":"alpha"},{"row":4,"col":6,"x":6.25,"y":4.25,"r":0,"rx":0,"ry":0,"d":false,"h":1,"w":1,"color":"alpha"},{"row":4,"col":7,"x":7.25,"y":4.25,"r":0,"rx":0,"ry":0,"d":false,"h":1,"w":1,"color":"alpha"},{"row":4,"col":8,"x":8.25,"y":4.25,"r":0,"rx":0,"ry":0,"d":false,"h":1,"w":1,"color":"alpha"},{"row":4,"col":9,"x":9.25,"y":4.25,"r":0,"rx":0,"ry":0,"d":false,"h":1,"w":1,"color":"alpha"},{"row":4,"col":10,"x":10.25,"y":4.25,"r":0,"rx":0,"ry":0,"d":false,"h":1,"w":1,"color":"alpha"},{"row":4,"col":11,"x":11.25,"y":4.25,"r":0,"rx":0,"ry":0,"d":false,"h":1,"w":1,"color":"alpha"},{"row":4,"col":13,"x":12.25,"y":4.25,"r":0,"rx":0,"ry":0,"d":false,"h":1,"w":1.75,"color":"mod"},{"row":4,"col":14,"x":14,"y":4.25,"r":0,"rx":0,"ry":0,"d":false,"h":1,"w":1,"color":"accent"},{"row":4,"col":15,"x":15,"y":4.25,"r":0,"rx":0,"ry":0,"d":false,"h":1,"w":1,"color":"mod"},{"row":5,"col":0,"x":0,"y":5.25,"r":0,"rx":0,"ry":0,"d":false,"h":1,"w":1.25,"color":"mod"},{"row":5,"col":1,"x":1.25,"y":5.25,"r":0,"rx":0,"ry":0,"d":false,"h":1,"w":1.25,"color":"mod"},{"row":5,"col":2,"x":2.5,"y":5.25,"r":0,"rx":0,"ry":0,"d":false,"h":1,"w":1.25,"color":"mod"},{"row":5,"col":5,"x":3.75,"y":5.25,"r":0,"rx":0,"ry":0,"d":false,"h":1,"w":6.25,"color":"alpha"},{"row":5,"col":10,"x":10,"y":5.25,"r":0,"rx":0,"ry":0,"d":false,"h":1,"w":1.25,"color":"mod"},{"row":5,"col":12,"x":11.25,"y":5.25,"r":0,"rx":0,"ry":0,"d":false,"h":1,"w":1.25,"color":"mod"},{"row":5,"col":13,"x":13,"y":5.25,"r":0,"rx":0,"ry":0,"d":false,"h":1,"w":1,"color":"accent"},{"row":5,"col":14,"x":14,"y":5.25,"r":0,"rx":0,"ry":0,"d":false,"h":1,"w":1,"color":"accent"},{"row":5,"col":15,"x":15,"y":5.25,"r":0,"rx":0,"ry":0,"d":false,"h":1,"w":1,"color":"accent"}]}}